yamlcleaner/__init__.py
yamlcleaner/cli.py
yamlcleaner-0.1.2.dist-info/licenses/LICENSE.MD
yamlcleaner-0.1.2.dist-info/METADATA
yamlcleaner-0.1.2.dist-info/WHEEL
yamlcleaner-0.1.2.dist-info/entry_points.txt
yamlcleaner-0.1.2.dist-info/top_level.txt
yamlcleaner-0.1.2.dist-info/RECORD
