Metadata-Version: 2.4
Name: yamlcleaner
Version: 0.1.2
Summary: Un outil CLI pour nettoyer les fichiers YAML en supprimant les commentaires
Author-email: Funasitien <hello@funa.dev>
License-Expression: MIT
Requires-Python: >=3.7
License-File: LICENSE.MD
Requires-Dist: colorama
Dynamic: license-file
